{
  "title": "Kan människan fulländas?",
  "arranger": "Cusanus, Teologiska institutionen, Uppsala universitet",
  "times": [
    {
      "start": "2017-07-03T07:30:00.000Z",
      "end": "2017-07-03T08:30:00.000Z"
    }
  ],
  "type": "Samtal",
  "area": "Forskning",
  "language": "Svenska",
  "location": "Uppsala universitet, Campus Gotland, Cramérgatan 3",
  "tags": [
    "Forskning och utbildning",
    "Humaniora",
    "Mänskliga rättigheter",
    "Religion"
  ],
  "description": "Enligt transhumanismen lider människan av en mängd onödiga svagheter som innebär lidande men som med teknikens hjälp är möjliga att övervinna. Är det möjligt att på olika sätt förbättra den mänskliga naturen mot en allt större fulländning? Och – är det önskvärt?",
  "extendedDescription": "Ett samtal inom området relationen mellan religion, naturvetenskap och etik.\n\n",
  "id": "44660"
}