{
  "title": "Maten, jorden, havet och klimatet – leder den nya strategin till en hållbar livsmedelsförsörjning?",
  "arranger": "Ekobanken, Trialog Tankesmedja",
  "times": [
    {
      "start": "2017-07-06T14:00:00.000Z",
      "end": "2017-07-06T15:50:00.000Z"
    }
  ],
  "type": "Seminarium",
  "area": "Hållbarhet",
  "language": "Svenska",
  "location": "Uppsala universitet, Campus Gotland, Cramérgatan 3",
  "tags": [
    "Havet",
    "Jordbruk",
    "Klimat",
    "Mat"
  ],
  "description": "En hållbar livsmedelsförsörjning hör till det allra viktigaste. Globalt måste vi säkra tillräckligt med näringsriktig mat åt alla. Men om maten produceras på ett ekologiskt ansvarslös sätt blir det ohållbart. Får vi nu en livsmedelsstrategi som säkrar en ekologiskt hållbar livsmedelsförsörjning?",
  "extendedDescription": "Man räknar med att livsmedelsproduktionen globalt svarar för 25% av våra totala klimatutsläpp. Jordbruket i de nordiska länderna svarar dessutom för 50% av Östersjöns övergödning. Både i Sverige och internationellt har vi erfarenhet av att det specialiserade handelsgödselberoende jordbruket långsiktigt utarmar jordens bördighet. Ändliga naturresurser förbrukas samtidigt som också matens kvalitet och näringsinnehåll utarmas. Användningen av kemiska bekämpningsmedlen leder till irreversibla skador på den biologiska mångfalden.\nPå detta seminarium diskuterar vi hur vi kan säkra en tillräcklig försörjning av näringsriktig mat på ett ekologiskt hållbart sätt.  Räcker vår nya livsmedelsstrategi till för att uppnå målen. Vi får frågan belyst ur vetenskaplig synpunkt samt ur praktisk erfarenhet så som offentlig mathållning och odling.  Vi får även höra vad politikerna vill göra.\n",
  "id": "44911"
}