{
  "title": "Nyanlända startar företag, bra för jobb och för integration",
  "arranger": "NyföretagarCentrum Sverige",
  "times": [
    {
      "start": "2017-07-06T10:15:00.000Z",
      "end": "2017-07-06T11:00:00.000Z"
    }
  ],
  "type": "Seminarium",
  "area": "Näringsliv",
  "language": "Svenska",
  "location": "Clarion Hotel Wisby, Strandgatan 6",
  "tags": [
    "Entreprenörskap",
    "Hållbart samhälle",
    "Integration",
    "Nya svenskar",
    "Näringsliv"
  ],
  "description": "30% av NyföretagarCentrums kunder är födda utomlands. Vi vet att många av våra nyanlända svenskar är mycket företagsamma och vill starta eget. Här finns en gynnsam utveckling för jobbskapande och integration. Hur kan vi underlätta för denna grupp att försörja sig själv och andra via eget företag?",
  "extendedDescription": "Hur tillvaratar vi deras företagsamhet vilket samtidigt hjälper till med integrationen?",
  "id": "45194"
}