{
  "title": "Mentorskap - framgångsrecept för nyföretagande?",
  "arranger": "NyföretagarCentrum Sverige",
  "times": [
    {
      "start": "2017-07-04T11:00:00.000Z",
      "end": "2017-07-04T11:45:00.000Z"
    }
  ],
  "type": "Seminarium",
  "area": "Näringsliv",
  "language": "Svenska",
  "location": "Strandvägen 4",
  "tags": [
    "Entreprenörskap",
    "Företagande",
    "Ideellt arbete",
    "Mentorskap",
    "Tillväxt"
  ],
  "description": "Mentorskap vet vi är en starkt bidragande faktor till utveckling, högre överlevnad och ekonomisk tillväxt. Många försöker men inte alla lyckas. Vad är utmaningarna för att få ett lyckat mentorskap som hjälper de nya företagen utvecklas?",
  "extendedDescription": "Många försöker men inte alla lyckas. Vad är utmaningarna för ett mentorskapsprogram och vad krävs för att lyckas? Vårt program når år ut och år in hög kvalitet i undersökningar. Vad är hemligheten?\n\n\n",
  "id": "45200"
}