{
  "title": "Sexuella brott mot barn kan ge livslångt lidande.",
  "arranger": "Brottsofferjouren",
  "times": [
    {
      "start": "2017-07-05T10:30:00.000Z",
      "end": "2017-07-05T11:30:00.000Z"
    }
  ],
  "type": "Seminarium",
  "area": "Mänskliga rättigheter",
  "language": "Svenska",
  "location": "Uppsala universitet, Campus Gotland, Cramérgatan 3",
  "tags": [
    "Barn och ungdomar",
    "Kvinnofrid",
    "Rättsväsende",
    "Sexuella övergrepp",
    "Våld"
  ],
  "description": "Allvaret i sexuella brott mot barn är högt – men samhällets prioritering av brottet är lågt. Vi bjuder in till seminarium följt av ett panelsamtal med politiker och sakkunniga. ",
  "id": "45300"
}