{
  "title": "Hur arbetar fastighetsbranschen med miljömässig hållbarhet?",
  "arranger": "Business Arena Almedalen, Fastighetsnytt Förlags AB",
  "times": [
    {
      "start": "2017-07-05T11:30:00.000Z",
      "end": "2017-07-05T12:00:00.000Z"
    }
  ],
  "type": "Seminarium",
  "area": "Byggande",
  "language": "Svenska",
  "location": "Supper, restaurang, Strandgatan 9",
  "tags": [
    "Fastighetsbranschen",
    "Samhällsbyggande"
  ],
  "description": "Den globala uppvärmningen fortsätter oberoende av om väljare i ett land tröttnar på ämnet. Den svenska fastighetsbranschen ligger långt framme när det gäller lösningar som är positiva för miljön och när det gäller att hushålla med resurser.",
  "extendedDescription": "I den här fördjupningen diskuterar vi aktuella exempel från samhällsbyggnadsområdet.",
  "id": "45444"
}