{
  "title": "Varför arbetar vi? Behöver vi arbeta i framtiden?",
  "arranger": "Tidningen Syre",
  "times": [
    {
      "start": "2017-07-03T08:00:00.000Z",
      "end": "2017-07-03T08:55:00.000Z"
    }
  ],
  "type": "Seminarium",
  "area": "Sysselsättning/arbetsmarknad",
  "language": "Svenska",
  "location": "Södra Kyrkogatan 6",
  "tags": [
    "Arbetsmarknadsfrågor",
    "Ekonomi",
    "Hållbart samhällsbyggande",
    "Välfärd"
  ],
  "description": "Alla partiet har de senaste 30 åren tävlat om vem som kan skapa flest jobb. Under samma period har vi fördubblat produktionseffektiviteten och arbetslösheten har ökat, oavsett färg på regeringen. Gör automatiseringen att vi kan jobba mindre och ska vi i så fall hitta på nya jobb eller bara slappa?",
  "extendedDescription": "Alla riksdagspartiet har de senaste 30 åren tävlat om vem som kan skapa flest jobb. Under samma period har vi fördubblat produktionseffektiviteten, det vill säga vi kan göra lika mycket med hälften så mycket jobb. Och arbetslösheten har trots det bara ökat, oavsett färg på regeringen. Gör automatiseringen att vi kan jobba mindre? Och om det är så att maskinerna stjäl våra jobb, ska vi hitta på nya då eller bara slappa? Är arbetet ett självändamål eller bara ett medel och om det senare medel för att nå vad?",
  "id": "45571"
}