{
  "title": "Nästa generation av skolledarutbildning – vad kommer efter rektorsprogrammet?",
  "arranger": "Mittuniversitetets rektorsprogram",
  "times": [
    {
      "start": "2017-07-05T13:00:00.000Z",
      "end": "2017-07-05T14:00:00.000Z"
    }
  ],
  "type": "Seminarium",
  "area": "Utbildning",
  "language": "Svenska",
  "location": "Uppsala universitet, Campus Gotland, Cramérgatan 3",
  "tags": [
    "Skola",
    "Skolforskning",
    "Skolledare",
    "Skolpolitik",
    "Skolutveckling"
  ],
  "description": "Skolkommissionens betänkande lyfter fram den professionella utveckling som utvecklingsområde. Det talas om inrättande av en nationell funktion för lärar- och skolledarutveckling liksom ett nationellt professionsprogram för lärare och skolledare. Vad innebär detta för utbildningen?",
  "extendedDescription": "Den 5 juli kl. 12:15-17:00 arrangerar Mittuniversitetets rektorsprogram Skolledarutbildningens dag. Under seminariedagen behandlas skolledarrollens komplexitet och vilka konsekvenser denna får för programmets innehåll och utförande. Hur får vi elever att må bättre genom förebyggande elevhälsoarbete? Hur har skolledare det egentligen i sin vardag? Hur kan verksamhetsutveckling och pedagogiskt ledarskap i praktiken utgöra utgångspunkt för utbildningen och hur påverkar utbildningen det pedagogiska ledarskapet i vardagen? Vidare förs, med utgångspunkt i Skolkommissionens betänkande, en debatt om hur nästa generation av skolledarutbildning kommer att vara uppbyggd. Rektorsutbildare från hela landet, med flera, medverkar.",
  "id": "45597"
}