{
  "title": "Åtkomliga bostäder för alla - hur kan nya ekonomiska modeller vara en lösning?",
  "arranger": "Malmö stad - en del av Öresundshuset",
  "times": [
    {
      "start": "2017-07-05T11:15:00.000Z",
      "end": "2017-07-05T12:00:00.000Z"
    }
  ],
  "type": "Seminarium",
  "area": "Byggande",
  "language": "Svenska",
  "location": "Hästgatan 1",
  "tags": [
    "Bostadsförsörjning",
    "Bostadspolitik",
    "Finansiering",
    "Hållbar stadsutveckling",
    "Social hållbarhet"
  ],
  "description": "Det finns en grupp av människor som befinner sig i en gråzon och som står utanför eller inte kan komma vidare på bostadsmarknaden. De har inte eget kapital eller faller inte under det sociala trygghetsnätet. Hur säkrar stat, bransch och kommun bostäder för dessa människor? ",
  "extendedDescription": "Vilka ekonomiska modeller finns och kan utvecklas?",
  "id": "45663"
}