{
  "title": "Lärarnas flykt - kommunernas kompetenskaos",
  "arranger": "Malmö stad - en del av Öresundshuset",
  "times": [
    {
      "start": "2017-07-04T07:00:00.000Z",
      "end": "2017-07-04T07:45:00.000Z"
    }
  ],
  "type": "Seminarium",
  "area": "Utbildning",
  "language": "Svenska",
  "location": "Hästgatan 1",
  "tags": [
    ""
  ],
  "description": "För Malmö stad är växande befolkning, ökande urbanisering och boendesegregation centrala utmaningar. Löser skolkommissionens förslag kompetensförsörjningen inom pedagogiska yrken? Hur omsätter vi utvecklingsarbetet som följer av \"Nationell samling för skolan\"?\n\n\n",
  "id": "45667"
}