{
  "title": "Konvertit eller inte? Vem avgör tron hos asylsökande?",
  "arranger": "(G) som i Gud, Dagen, Frälsningsarmén, Pingströrelsen",
  "times": [
    {
      "start": "2017-07-04T07:00:00.000Z",
      "end": "2017-07-04T08:15:00.000Z"
    }
  ],
  "type": "Seminarium",
  "area": "Mänskliga rättigheter",
  "language": "Svenska",
  "location": "Krukmakarens hus, Frälsningsarmén, Mellangatan 21",
  "tags": [
    "Asyl",
    "Konvertit",
    "Migration",
    "Mänskliga rättigheter",
    "Religion"
  ],
  "description": "Organisationen Open Doors har kartlagt våld och trakasserier på flyktingmottagningar mot kristna asylsökande, inklusive konvertiter, som kommit till Sverige. Vad gör vi åt problemet? Och hur påverkas asylprocessen av att någon har konverterat till kristen tro? Vi diskuterar kartläggningen.",
  "id": "45953"
}