{
  "title": "Rörelserna och människorna som format det moderna svenska hatet",
  "arranger": "Almedalsbiblioteket, Natur & Kultur",
  "times": [
    {
      "start": "2017-07-04T17:00:00.000Z",
      "end": "2017-07-04T18:00:00.000Z"
    }
  ],
  "type": "Samtal",
  "area": "Demokrati",
  "language": "Svenska",
  "location": "Almedalsbiblioteket, Cramérgatan 5",
  "tags": [
    "Rasism",
    "Våldsbejakande extremism"
  ],
  "description": "Två hatfyllda rörelser – den militanta islamismen och de islamfientliga organisationerna – har fått stor makt att påverka det offentliga samtalet. Hur ska vi förstå och hantera detta verbala och tidvis fysiska våld? ",
  "extendedDescription": "Vad är det egentligen som har hänt med Sverige? Gellert Tamas berättar om personer och företeelser som varit centrala i framväxten av det svenska hatet. Han skildrar också självmordsbombare, mördare och svenska jihadkrigare. Det handlar om människor som format det moderna svenska hatet. Tamas har gjort en djuplodande granskning av två \"huvudfiender\" i en påstådd kamp mellan civilisationer – som i själva verket både behöver och använder sig av varandra.",
  "id": "46111"
}