{
  "title": "Vem ställer in den moraliska kompassen?",
  "arranger": "Grant Thornton",
  "times": [
    {
      "start": "2017-07-04T11:30:00.000Z",
      "end": "2017-07-04T12:30:00.000Z"
    }
  ],
  "type": "Samtal",
  "area": "Näringsliv",
  "language": "Svenska",
  "location": "Strandvägen, H513",
  "tags": [
    "Ansvar",
    "Framtid",
    "Ideellt arbete",
    "Samhällsnytta",
    "Välfärd"
  ],
  "description": "Idag ser vi ett alltmer tudelat samhälle där vi verkar glida ifrån varandra värderingsmässigt. Sker det en värdeförskjutning lokalt och globalt? Vilken roll och vilket ansvar ska civilsamhällets aktörer ta? Vi samtalar om vår framtida gemensamma värdegrund.",
  "id": "46116"
}