{
  "title": "Energiomställningen pågår nu – hur hittar vi de ekonomiska drivkrafterna?",
  "arranger": "Göteborgs Stad",
  "times": [
    {
      "start": "2017-07-03T12:00:00.000Z",
      "end": "2017-07-03T13:00:00.000Z"
    }
  ],
  "type": "Seminarium",
  "area": "Energi",
  "language": "Svenska",
  "location": "Strandvägen, H528",
  "tags": [
    "Affärsutveckling",
    "Energi",
    "Fossilfritt",
    "Hållbar stadsutveckling",
    "Innovation"
  ],
  "description": "Göteborgs Stad utvecklar tillsammans med åtta partners en unik lokal handelsplats för el, värme och kyla. Projektet Fossil-free Energy Districts optimerar energianvändningen. Hur bidrar en lokal energimarknad mellan fastigheter till effektivare resursutnyttjande? Vilka är handelsplatsens utmaningar?",
  "extendedDescription": "EU-projektet Fossil-free energy districts, FED, är en innovativ satsning av Göteborgs Stad för att minska energianvändningen och beroendet av fossila bränslen i fastigheter. En unik lokal handelsplats för el, fjärrvärme och fjärrkyla utvecklas tillsammans med åtta starka partners. \nEnergi kommer att köpas och säljas mellan fastigheter sinsemellan likaväl som mellan fastigheter och energibolag. Energin mellanlagras bland annat i byggstommar, batterier och ackumulatortankar. \nUnder 2017−2019 utgör Chalmers Campus Johanneberg själva testbädden. FED valdes ut i stor konkurrens av Urban Innovative Actions, Europakommissionens nya initiativ för att låta städer testa lösningar för sina utmaningar.",
  "id": "46145"
}