{
  "title": "Vem är intresserad av livstilsbehandling av migrän?",
  "arranger": "MI Migrän Info AB",
  "times": [
    {
      "start": "2017-07-04T07:30:00.000Z",
      "end": "2017-07-04T08:30:00.000Z"
    }
  ],
  "type": "Seminarium",
  "area": "Forskning",
  "language": "Svenska",
  "location": "Uppsala universitet, Campus Gotland, Cramérgatan 3",
  "tags": [
    "Forskning",
    "Hälsa",
    "Hälso- och sjukvård",
    "Läkemedel",
    "Mat"
  ],
  "description": "Mer än 10 % av befolkningen lider av migrän. Ingen vet orsaken till sjukdomen och sjukvården behandlar genom att lindra symptomen med läkemedel. Flera är hjälpta utan läkemedel genom att hålla blodsockret stabilt - men varför intresserar sig inte forskare och sjukvård för det?",
  "extendedDescription": "Efter många år som frisk migränpatient genom livsstilsåtgärder och två böcker om detta undrar juristen och författaren Kristina Ahlström varför forskarna i Sverige inte visar intresse för en helt biverkningsfri metod. Forskare om andra sjukdomar talar i dag om vikten av att äta bra och röra sig, inte minst för att förhindra diabetes typ 2. – Genom att hålla blodsockret stabilt varje dag undviker Kristina Ahlström migrän. Teorin bakom är att en överaktiv bukspottkörtel producerar för mycket insulin vilket startar en kemisk reaktion som utlöser smärtan. – \"Jag vet inte om teorin håller, men metoden har hjälpt mig i över 26 år\" säger Kristina Ahlström. Fler som provar metoden blir hjälpta men forskarna och sjukvården visar inget intresse. \"Stör jag i affärerna\" undrar Kristina Ahlström. För vem förlorar på att patienterna blir friska utan läkemedel?",
  "id": "46495"
}