{
  "title": "Ungas beställning till samhället",
  "arranger": "Sveriges Psykologförbund, Psykisk Hälsa Huset",
  "times": [
    {
      "start": "2017-07-05T13:00:00.000Z",
      "end": "2017-07-05T14:30:00.000Z"
    }
  ],
  "type": "Seminarium",
  "area": "Barn/ungdom",
  "language": "Svenska",
  "location": "Kinbergs plats 8",
  "tags": [
    "Barn och ungdomar",
    "Psykisk ohälsa"
  ],
  "description": "Psykisk ohälsa bland unga ökar. Politiker, professionella och myndigheter gör mycket som är bra men ofta i varsitt stuprör och utifrån vad de tycker behövs för barn och unga. Vad skulle ske om barn och unga, utifrån egna erfarenheter, fick möjlighet att skicka en beställning till samhället?",
  "extendedDescription": "Levererar samhället vad unga behöver? Om barn och unga skulle skicka en beställning till samhället, hur skulle den se ut? Mottagaren blir då samhället som helhet. Inte stuprör som elevhälsa, primärvård, socialtjänst, barnpsykiatri etc. Utifrån denna ”beställning” blir det då yrkesgruppernas och organisationernas uppgift att identifiera hur de skulle kunna bidra med sin expertkunskap. Politikerna får då svara på hur de, mot bakgrund av behoven och de tillgångar som finns, skulle kunna bidra med en organisation för att svara mot behoven.\n \n",
  "id": "46501"
}