{
  "title": "Rör inte min källa! Hur ser vi till att den nya lagen om meddelarskydd får genomslag i praktiken?",
  "arranger": "Journalistförbundet, Föreningen Grävande Journalister",
  "times": [
    {
      "start": "2017-07-05T12:30:00.000Z",
      "end": "2017-07-05T13:30:00.000Z"
    }
  ],
  "type": "Seminarium",
  "area": "Yttrandefrihet",
  "language": "Svenska",
  "location": "Strandgatan 19",
  "tags": [
    "Hälso- och sjukvård",
    "Journalistik",
    "Media",
    "Skola",
    "Yttrandefrihet"
  ],
  "description": "Den 1 juli 2017 träder en ny lag i kraft som ger privatanställda inom offentligt finansierad vård, skola och omsorg meddelarskydd. Anställda får nu ett utökat skydd om de vill lämna uppgifter till media och journalister får större möjligheter att skydda källor. Men vet arbetsgivarna vad som gäller?",
  "extendedDescription": "Kunskapen om meddelarfrihet och meddelarskydd bland chefer i offentlig sektor är ganska låg. Nu har vi en ny lag som utökar meddelarskyddet till att även gälla privatanställda inom offentligt finansierad vård, skola och omsorg. Här är kunskapen bland cheferna ännu lägre. Många anställda vet inte och vågar inte prata med journalister på grund av felaktig information från arbetsgivarna. \n\nHur ser vi till att fler vågar lämna uppgifter media? Vilken effekt får lagen på stora börsnoterade välfärdsföretag? Och borde meddelarskyddet utvidgas till att gälla alla anställda på alla företag?\n\nVi diskuterar dessa frågor och visar upp exempel på när meddelarskyddet fungerat bra och när det fungerat dåligt. \n\nUnder Almedalsveckan går Journalistförbundets meddelarskyddsambassadörer runt och utbildar chefer i välfärdsföretag om vad som gäller. På seminariet får ni också höra mer om deras kunskap och åsikter om meddelarskydd. ",
  "id": "46532"
}