{
  "title": "Krympande utrymme för hbtq-aktivism",
  "arranger": "RFSL",
  "times": [
    {
      "start": "2017-07-06T06:00:00.000Z",
      "end": "2017-07-06T06:45:00.000Z"
    }
  ],
  "type": "Samtal",
  "area": "Yttrandefrihet",
  "language": "Svenska",
  "location": "Södertorg 17",
  "tags": [
    "Föreningsliv",
    "Hbtq",
    "Hot",
    "Säkerhet",
    "Våldsbejakande extremism"
  ],
  "description": "Hur vanligt är det med aktivister och grupper som motsätter sig hbtq-personers rättigheter och som är beredda att ta till hot och våld? Påverkar dessa grupperingar hbtq-rörelsens möjlighet att arbeta? Och vad kan göras för att motverka att utrymmet för hbtq-aktivism minskas?",
  "id": "46606"
}