{
  "title": "Psykisk e-hälsa – vad kan vi förvänta oss i framtiden?",
  "arranger": "Offentliga Affärer, 21 Century Mobile",
  "times": [
    {
      "start": "2017-07-05T12:00:00.000Z",
      "end": "2017-07-05T12:45:00.000Z"
    }
  ],
  "type": "Debatt",
  "area": "Digitalisering",
  "language": "Svenska",
  "location": "Strandvägen 4",
  "tags": [
    "Digital hälsa",
    "Digitalisering",
    "E-hälsa",
    "Psykisk ohälsa",
    "Psykologi"
  ],
  "description": "Den psykiska ohälsan i samhället ökar i snabb takt och med otillräckliga resurser får många som är i behov av kontakt med sjukvården vänta alldeles för länge på behandling. Hur kan digitala verktyg hjälpa sjukvård och patienter? Paneldebatt om psykisk ohälsa och tillämpning av digitala verktyg. ",
  "id": "46648"
}