{
  "title": "Regionerna tar plats i stadsplaneringen – hur arbetar de som lyckats?",
  "arranger": "Business Arena Almedalen, Fastighetsnytt Förlags AB",
  "times": [
    {
      "start": "2017-07-03T07:30:00.000Z",
      "end": "2017-07-03T08:00:00.000Z"
    }
  ],
  "type": "Seminarium",
  "area": "Byggande",
  "language": "Svenska",
  "location": "Supper, restaurang, Strandgatan 9",
  "tags": [
    "Fastighetsbranschen",
    "Samhällsbyggande"
  ],
  "description": "Sveriges regioner har de senaste åren fått en allt större roll i debatten, i takt med att städerna blir allt trängre och infrastrukturen allt viktigare för var människor och företag väljer att etablera sig. Hur ska man arbeta när stadsplaneringen går allt mer åt det regionala hållet? ",
  "extendedDescription": "Vilka utmaningar stöter kommuner och företag på? Finns det några risker med utvecklingen? ",
  "id": "46873"
}