{
  "title": "En digital revolution - hur påverkar den fastigheter och städer?",
  "arranger": "Business Arena Almedalen, Fastighetsnytt Förlags AB",
  "times": [
    {
      "start": "2017-07-04T13:00:00.000Z",
      "end": "2017-07-04T13:30:00.000Z"
    }
  ],
  "type": "Seminarium",
  "area": "Byggande",
  "language": "Svenska",
  "location": "Supper, restaurang, Strandgatan 9",
  "tags": [
    "Fastighetsbranschen",
    "Samhällsbyggande"
  ],
  "description": "En av de sektorer i samhället där digitaliseringen kanske kommer att påverka mest är fastigheter och samhällsbyggnad. Det kan handla om hissar som känner igen de som arbetar i en byggnad, självkörande bilar på gatorna och hus som själva kan tala om var ett tekniskt fel uppstår. ",
  "extendedDescription": "Vi försöker analysera effekterna av den pågående utvecklingen, vara lite lagom visionära och ge ett branschperspektiv på den digitala utvecklingen.",
  "id": "46922"
}