{
  "title": "Så införde vi vegonorm i vår organisation",
  "arranger": "Svensk mat- och miljöinformation, Vegonorm",
  "times": [
    {
      "start": "2017-07-04T06:00:00.000Z",
      "end": "2017-07-04T06:45:00.000Z"
    }
  ],
  "type": "Samtal",
  "area": "Mat",
  "language": "Svenska",
  "location": "Betty Petterssons Hus, UUCG, Kaserngatan 1",
  "tags": [
    "Hälsa",
    "Miljö",
    "Vego",
    "Växtbaserad"
  ],
  "description": "Vi pratar med representanter för organisationer som har vegonorm i sin verksamhet, det vill säga vegetarisk mat som standard. Hur gick det till när de införde vegonorm? Vad fungerar bra och finns det några fallgropar man bör undvika?",
  "extendedDescription": "Vi får tips om hur vi själva kan arbeta för vegonorm i organisationer där vi arbetar och är aktiva. ",
  "id": "47067"
}