{
  "title": "Raka svar med Anna Kinberg Batra om Moderaternas framtid",
  "arranger": "Expressen",
  "times": [
    {
      "start": "2017-07-08T12:30:00.000Z",
      "end": "2017-07-08T12:45:00.000Z"
    }
  ],
  "type": "Samtal",
  "area": "Demokrati",
  "language": "Svenska",
  "location": "Donners plats, H409",
  "tags": [
    "Moderaterna",
    "Partiledare"
  ],
  "description": "Allt fler väljare flyr Moderaterna och förtroendet för partiledaren är lågt. Hur ska hon vända siffrorna inför valet 2018 och kan hon bygga upp ett förtroende?",
  "id": "47230"
}