{
  "title": "Refotografering - landskap under påverkan av klimatförändringar",
  "arranger": "Forskningsrådet Formas",
  "times": [
    {
      "start": "2017-07-06T08:00:00.000Z",
      "end": "2017-07-06T09:00:00.000Z"
    }
  ],
  "type": "Samtal",
  "area": "Klimat/miljö",
  "language": "Svenska",
  "location": "Strandvägen, H523",
  "tags": [
    "Forskning",
    "Historia",
    "Humaniora",
    "Klimat",
    "Miljö"
  ],
  "description": "Hur kan fotografiska bilder användas för att visa människan i relation till miljön? Hur förändras vår syn på natur och landskap över tid? Hur fungerar fotografier som vetenskapliga dokument och som konstnärliga representationer? Hur kan fotoarkiv och -samlingar levandegöras?",
  "extendedDescription": "Tyrone Martinsson arbetar med fotografins historia och samtid i relation till miljö och landskap (environmental photography). Han berättar om sitt arbete med re-fotografering av landskapsvyer där förändring över tid blir tydliga och om upplevelser av klimatförändringar i Arktis genom fältarbeten och visar ett urval av bilder. Forskningens utgångspunkt är fotohistoriens koppling till modernitetens utveckling. Under de senaste åren har Tyrone Martinsson bedrivit forskning om Arktis och refotografiska metoder för tvärvetenskapliga studier som rör klimat, miljö och historiebeskrivningar av det polara landskapet. ",
  "id": "47247"
}