{
  "title": "Behövs en nationell testbäddsportal för digitaliserat samhällsbyggande?",
  "arranger": "Sustainable Innovation",
  "times": [
    {
      "start": "2017-07-05T12:45:00.000Z",
      "end": "2017-07-05T13:45:00.000Z"
    }
  ],
  "type": "Seminarium",
  "area": "Byggande",
  "language": "Svenska",
  "location": "Teaterskeppet, fartyg",
  "tags": [
    "Energieffektivisering",
    "Hållbart samhällsbyggande",
    "Innovation",
    "Samhällsnytta",
    "Testbädd"
  ],
  "description": "Finns det samordningsbehov av landets demo- och innovationsplattformar? Hur uppnås rätt effekter av initiativen när antalet testbäddar snart överstiger 200st? Diskussion om samordning för att förenkla test, verifiering, optimera nyttjandet och snabba upp kommersialiseringen av svenska innovationer.",
  "id": "47282"
}