{
  "title": "Den svenska biogasen är hotad – vad krävs av beslutsfattarna?",
  "arranger": "Region Skåne - en del av Öresundshuset",
  "times": [
    {
      "start": "2017-07-03T07:00:00.000Z",
      "end": "2017-07-03T07:45:00.000Z"
    }
  ],
  "type": "Seminarium",
  "area": "Hållbarhet",
  "language": "Svenska",
  "location": "Hästgatan 1",
  "tags": [
    "Bioenergi",
    "Bränsle",
    "EU",
    "Lagstiftning"
  ],
  "description": "EU-ländernas olika stödsystem gör att biogas som importeras till Sverige har ett lägre pris. Den svenska biogasen är därför hotad. Utan inhemsk biogasproduktion påverkas jobben, miljön, nya innovationer och landsbygden negativt. Vad krävs för att bevara och utveckla den svenska biogasproduktionen? ",
  "extendedDescription": "Sveriges satsningar på biogas har genom åren visat bredden av de samhällsnyttor som biogasproduktionen ger, exempelvis jobb på landsbygden, omhändertagande av avfall, minskad klimatpåverkan, cirkulär ekonomi, innovationer, en bättre havsmiljö och gödsel till ekologiskt jordbruk. Dessa samhällsnyttor är nu hotade på grund av EU-ländernas olika stödsystem som gör att den biogas som importeras till Sverige har ett betydligt lägre pris än den biogas som produceras i Sverige.\n\nFör att bevara den svenska biogasen behöver den inhemska produktionen ges rimliga villkor i konkurrensen med produktionen i andra EU-länder. Och för att utveckla biogasproduktionen, och dess samhällsnyttor, i Sverige behöver branschen få tydliga och långsiktiga spelregler att förhålla sig till. Vad krävs av beslutsfattarna för att bevara och utveckla den svenska biogasproduktionen?\n",
  "id": "47335"
}