{
  "title": "Hur vill de olika partierna gå vidare efter den stora regionbildningskollapsen?",
  "arranger": "AlmeDalarna",
  "times": [
    {
      "start": "2017-07-03T12:00:00.000Z",
      "end": "2017-07-03T13:30:00.000Z"
    }
  ],
  "type": "Samtal",
  "area": "Regionfrågor",
  "language": "Svenska",
  "location": "S:t Hans Café, S:t Hansplan 2",
  "tags": [
    "Regional utveckling",
    "Stad–land konflikt",
    "Urbanisering"
  ],
  "description": " Regioner utanför storstäderna bidrar via industri och andra näringar med naturresurser, jobb och tillväxt i hela landet. Ändå benämns de som ”skräpytor” eller ”tärande” delar av landet av vissa i debatten. Vilka är de viktigaste förslagen för att bidra till att hela landet kan leva?",
  "extendedDescription": "”Tillväxtmotorer eller det postgeografiska samhället?”. Det är temat på den satsning som vi tillsammans, Dalarnas kommuner, Region Dalarna och ett stort antal samverkanspartners från vår region, gör i år under Almedalsveckan. Det är 8 miljoner människor som inte bor i Sveriges storstäder.",
  "id": "47554"
}