{
  "title": "Förebyggande hälsa - utmaningar, skillnader och effekt",
  "arranger": "AlmeDalarna",
  "times": [
    {
      "start": "2017-07-03T09:45:00.000Z",
      "end": "2017-07-03T10:45:00.000Z"
    }
  ],
  "type": "Samtal",
  "area": "Regionfrågor",
  "language": "Svenska",
  "location": "S:t Hans Café, S:t Hansplan 2",
  "tags": [
    "Hälsa",
    "Regional utveckling"
  ],
  "description": "Med hälsoförebyggande insatser kan såväl människors ohälsa som samhällets kostnader i framtiden minska kraftigt. Många talar om vikten av detta, men hur ser de faktiska hälsoförebyggande insatserna ut? Hur skiljer sig de förebyggande hälsoinsatserna mellan olika regioner och kommuner?",
  "extendedDescription": "”Tillväxtmotorer eller det postgeografiska samhället?”. Det är temat på den satsning som vi tillsammans, Dalarnas kommuner, Region Dalarna och ett stort antal samverkanspartners från vår region, gör i år under Almedalsveckan. Det är 8 miljoner människor som inte bor i Sveriges storstäder.\n\nRegioner utanför storstäderna bidrar via industri och andra näringar med naturresurser, jobb och tillväxt i hela landet. Ändå benämns de som ”skräpytor” eller ”tärande” delar av landet av vissa i debatten, och delar av landet drabbas av utflyttning. ",
  "id": "47561"
}