{
  "title": "Framtidens läromedel är redan här men vad väljer skolorna?",
  "arranger": "Atea Sverige AB",
  "times": [
    {
      "start": "2017-07-04T11:45:00.000Z",
      "end": "2017-07-04T12:30:00.000Z"
    }
  ],
  "type": "Seminarium",
  "area": "Utbildning",
  "language": "Svenska",
  "location": "Karamellboden, Södra Kyrkogatan 7",
  "tags": [
    "Digitalisering",
    "IT",
    "Läromedel",
    "Skolledare",
    "Skolutveckling"
  ],
  "description": "Digitala läromedel ger bättre förutsättningar för individanpassning, lärarna sparar tid och dessutom ges bättre förutsättningar för kollegialt lärande. Men hur ser det ut på skolorna idag? Väljer man tryckta eller digitala läromedel? Håller man fast vid den traditionella boken? ",
  "extendedDescription": "Skolan är inte digitaliserad bara för att en rad datorer finns på plats. Fullfölj digitaliseringen genom att ta ett samlat grepp även kring det pedagogiska innehållet. Skapa nya möjligheter med hjälp av en ny typ av digitala läromedel. Ta gärna med din egen dator om du vill testa själv. Seminariet vänder sig till dig som är intresserad av skolans digitalisering och vänder sig till dig som är skolledare, IKT-pedagog eller lärare. ",
  "id": "47746"
}