{
  "title": "Hur överbrygger vi gränshindren?",
  "arranger": "Region Värmland",
  "times": [
    {
      "start": "2017-07-04T08:00:00.000Z",
      "end": "2017-07-04T09:00:00.000Z"
    }
  ],
  "type": "Samtal",
  "area": "Internationella frågor",
  "language": "Svenska",
  "location": "Hamnplan, H228",
  "tags": [
    "EU",
    "Gränshinder",
    "Internationella frågor",
    "Norden",
    "Norge"
  ],
  "description": "Hur påverkas Sverige och Norge av gränsen? Vad kan vi göra för att utveckla möjligheterna över såväl lands- som EU-gränser? I ett samtal med representanter från Europeisk, nordisk, nationell och regional nivå lyfter vi vad gränshinder är idag och vilket arbete som görs för att överbrygga dem. ",
  "id": "47751"
}