{
  "title": "Så blir Sverige ett exportland av hållbar sjömat",
  "arranger": "RISE Research Institutes of Sweden",
  "times": [
    {
      "start": "2017-07-06T07:00:00.000Z",
      "end": "2017-07-06T07:50:00.000Z"
    }
  ],
  "type": "Föreläsning",
  "area": "Mat",
  "language": "Svenska",
  "location": "H10, Hästgatan 10A",
  "tags": [
    "Blå tillväxt",
    "Fiske",
    "Marin näringsutveckling",
    "Marina livsmedel",
    "Sjömat"
  ],
  "description": "Hållbart fiske och vattenbruk kan ge oss mer inhemsk och mer hälsosam mat och bidra till att omsätta livsmedelsstrategin till verklighet. Genom innovation och affärsutveckling har hållbar sjömat dessutom potential att bli vår nästa stora exportprodukt. ",
  "extendedDescription": "Vilka behov har företagen och hur kan politiken hjälpa till? RISE diskuterar med olika aktörer i livsmedelskedjan hur Sverige kan utveckla sjömatssektorn och profilera den som hållbar. \n\nVi startar 10.00, vid klockan 11:00 rundar vi av men fortsätter med arrangörsgruppen Maritim Mötesplats’ seminarium fram till 12:00. Samma tema i fokus dvs. ”Svensk sjömat för hållbar blå tillväxt\".\n\n\nSmakprover av rökt fisk, Clarias (på svenska afrikansk ålmal), odlad i Skåne i före detta ladugårdar som kan vara ett alternativ till rökt ål eller lax. ",
  "id": "47875"
}