{
  "title": "Klart jag vill veta hur det går! Är patienter mer positiva till kvalitetsregister än personalen?",
  "arranger": "Psykisk Hälsa Huset",
  "times": [
    {
      "start": "2017-07-07T09:00:00.000Z",
      "end": "2017-07-07T10:00:00.000Z"
    }
  ],
  "type": "Samtal",
  "area": "Vård och omsorg",
  "language": "Svenska",
  "location": "Kinbergs plats 8",
  "tags": [
    "Kvalitetshöjning",
    "Psykiatriregister",
    "Psykisk ohälsa",
    "Psykossjukdomar",
    "Verksamhetsutveckling"
  ],
  "description": "Vården måste släppa sina obehagskänslor inför att jämföras - till exempel i kvalitetsregister.\nAtt bli medveten om sina tillkortakommanden är startpunkten för förbättring.\nNu handlar det inte längre om inmatning av data utan om hur vi kan använda data i aktivt förbättringsarbete.",
  "extendedDescription": "Psykiatrin är ett område som tidigare varit svårt att mäta och följa upp. Kvalitetsregister är i dag det bästa vi har och de senaste åren har det skett en explosionsartad utveckling såväl avseende registreringsgrad, som kvalitet på de indikatorer som mäts.\nGenom att mäta, sammanställa statistik och följa upp resultat kan kvalitetsregister bidra till att förbättra vården - men det borde kunna gå fortare. \nHur skapas patientnytta med jämförelser och kontinuerlig uppföljning som patienter och personal kan ta del av och använda i vården? Hur kan vi skapa en ökad nyfikenhet och driv till kvalitetsutveckling i vården?\nKvalitetsregister kan användas integrerat och aktivt för löpande lärande, förbättring, forskning samt ledning och kunskapsstyrning för att tillsammans med individen skapa bästa möjliga hälsa, vård och omsorg.",
  "id": "47957"
}