{
  "title": "Talangekonomi",
  "arranger": "Nowa Kommunikation, DigJourney, Cordial",
  "times": [
    {
      "start": "2017-07-05T04:30:00.000Z",
      "end": "2017-07-05T05:30:00.000Z"
    }
  ],
  "type": "Seminarium",
  "area": "Digitalisering",
  "language": "Svenska",
  "location": "Rigagränd 1",
  "tags": [
    "Arbetsmarknad",
    "Digitalisering",
    "Framtid",
    "Inkludering",
    "Integritet"
  ],
  "description": "Talangekonomi. Eller jakten på supertalangerna. Vad ställer en allt mer digital framtid för krav på arbetskraften? Vad händer om talangerna inte hittas? Och vad händer med de som inte kvalar in i framtidsekonomin?",
  "id": "48228"
}