{
  "title": "Hur kan utveckling och innovation bidra till klimat- och hållbarhetsmålen?",
  "arranger": "Ålands landskapsregering, Ålandsbanken, South Pole Group",
  "times": [
    {
      "start": "2017-07-04T07:00:00.000Z",
      "end": "2017-07-04T08:00:00.000Z"
    }
  ],
  "type": "Seminarium",
  "area": "Hållbarhet",
  "language": "Svenska",
  "location": "Michael Sars, fartyg",
  "tags": [
    "Ekonomi",
    "Finansiering",
    "Hållbarhet",
    "Hållbart samhälle",
    "Innovation"
  ],
  "description": "Nordiska regeringar både på nationell och lokal nivå, företag och deras intressenter har satt höga och ambitiösa mål med sikte på klimatneutralitet, ett fossilfritt samhälle och FN:s hållbarhetsmål (SDG). Men vägen framåt kräver ledarskap, innovation och samarbete i nya former.",
  "extendedDescription": "Allt fler ställer också krav på att nå målet inom en bestämd tidsram mellan 2025 till 2050. Är finansmarknaderna redo att leverera på löftena från klimatöverenskommelsen i Paris med stora investeringar i både städer och företag? Och har städer, banker och andra intressenter det ledarskap som behövs för den stora omställning som ligger framför oss?",
  "id": "48370"
}