{
  "title": "Startskott inför valet 2018 – fortsättning",
  "arranger": "Kantar Sifo",
  "times": [
    {
      "start": "2017-07-04T13:15:00.000Z",
      "end": "2017-07-04T13:45:00.000Z"
    }
  ],
  "type": "Seminarium",
  "area": "Annat",
  "language": "Svenska",
  "location": "Hamnplan, H201",
  "tags": [
    "Analys",
    "Partiledare",
    "Politik",
    "Samhälle",
    "Val 2018"
  ],
  "description": "Hur ser riksdagspartiernas väljarpotential ut inför valet 2018? Partianhängares uppdelning, partisympatisörers identifikation med sina respektive partier presenteras. Vilka sakfrågor som väljarna anser viktigast avgör de olika partiernas hot och möjligheter?",
  "id": "48419"
}