{
  "title": "Hur ser Socialdemokraterna på pensionärernas villkor inför valet?",
  "arranger": "News55",
  "times": [
    {
      "start": "2017-07-05T05:00:00.000Z",
      "end": "2017-07-05T06:00:00.000Z"
    }
  ],
  "type": "Samtal",
  "area": "Äldre",
  "language": "Svenska",
  "location": "Strandvägen, H526_b",
  "tags": [
    "Framtid",
    "Pension",
    "Äldre"
  ],
  "description": "De största pensionärsorganisationerna har närmare 900 000 medlemmar. Det kan innebära tungan på vågen i ett osäkert val år 2018. Många upplever att kärnfrågorna för äldre - som pensionärers ekonomi, hälsa och åldersdiskriminering - inte prioriteras. Vi ställer partiet mot väggen.",
  "extendedDescription": "Annika Strandhäll (S) är sittande socialförsäkringsminister. Hon är just nu dessutom tillförordnad folkhälso-, sjukvårds- och idrottsminister. Hon frågas ut om partiets syn på äldrefrågor inför höstens val.\n",
  "id": "48464"
}