{
  "title": "Hur bygger man en skola för 540 elever till halva kostnaden?",
  "arranger": "Intressegrupp Passivhus Sverige",
  "times": [
    {
      "start": "2017-07-04T06:30:00.000Z",
      "end": "2017-07-04T07:30:00.000Z"
    }
  ],
  "type": "Seminarium",
  "area": "Byggande",
  "language": "Svenska",
  "location": "Blue Charm, fartyg",
  "tags": [
    "Ekonomi",
    "Energieffektivisering",
    "Fastigheter",
    "Hållbar stadsutveckling",
    "Hållbart samhälle"
  ],
  "description": "Många kommuner står inför stora investeringar i skolor, förskolor och andra samhällsnyttiga byggnader. Själva byggkostnaden är förstås en avgörande faktor, men minst lika viktigt att ha med i beräkningen är driftskostnaderna. Kan man bygga bra, kostnadseffektivt och energisnålt på en och samma gång?",
  "extendedDescription": "Flera nybyggda projekt visar att man kan bygga både bra, kostnadseffektivt och energisnålt. Kommunerna som satsar på rätt byggteknik sparar miljonbelopp varje år, både i byggkostnad och drift. Högåsskolan i Knivsta kostade mindre att bygga, och driftskostnaden är bara en femtedel jämfört med konventionellt nybyggda skolor. Flera nya projekt enligt samma princip är under byggnation. Laholms kommun satsar på en ny skola med idrottshall och kombinerar långsiktig kvalitet och energihushållning med höga livsvärden. Gemensamt för husen är att de är byggda enligt internationell passivhusstandard – en standard som är definierad och jämförbar i hela världen.",
  "id": "48607"
}