{
  "title": "Varför en regional nod för gestaltad livsmiljö?",
  "arranger": "Malmö stad",
  "times": [
    {
      "start": "2017-07-04T12:00:00.000Z",
      "end": "2017-07-04T12:45:00.000Z"
    }
  ],
  "type": "Seminarium",
  "area": "Hållbarhet",
  "language": "Svenska",
  "location": "Best Western Strand Hotel, Strandgatan 34",
  "tags": [
    "Arkitektur",
    "Design",
    "Gestaltad livsmiljö",
    "Hållbarhet",
    "Sysselsättning"
  ],
  "description": "Kraften i arkitektur, form och design används inte till fullo i formandet av människors gestaltade livmiljö. Frågan är för omfattande för en enskild aktör eller bransch att lösa. Hur kan en regional nod bidra till att forma en hållbar och gestaltad livsmiljö på nationell nivå över tid? ",
  "extendedDescription": "Kraften i arkitektur, form och design används inte till fullo i formandet av människors liv och vardag – i den gestaltade livsmiljön. Frågan om människors livsmiljö är för omfattande för en enskild aktör eller bransch att lösa. Därför behövs en ny samlad nationell politik för arkitektur, form och design. Ett komplement till den är regionala noder som samlar den kraft och kompetens som finns för att forma en hållbar och gestaltad livsmiljö över tid i hela Sverige. \nVarför behövs regionala noder för området Gestaltad livsmiljö i Sverige?\nHur utformar vi en struktur för synergier mellan befintliga kompetenser inom området?\nVilken betydelse har kunskap inom arkitektur, form och design för svensk sysselsättning och export och hur kan noderna stötta detta? \n",
  "id": "48680"
}