{
  "title": "Modern akutsjukvård - vem gör vad och hur vi skapar en säker och effektiv vård tillsammans?",
  "arranger": "Capio",
  "times": [
    {
      "start": "2017-07-04T09:30:00.000Z",
      "end": "2017-07-04T10:30:00.000Z"
    }
  ],
  "type": "Seminarium",
  "area": "Vård och omsorg",
  "language": "Svenska",
  "location": "Rosas Café, S:t Hansgatan 22",
  "tags": [
    "Samverkan",
    "Sjukvård",
    "Utveckling",
    "Vård och omsorg"
  ],
  "description": "Hur fungerar  ”en modern akutsjukvård”. Med nya vårdnivåer och ändrade uppdrag behöver vi hitta säkra och effektiva sätt att samverka med våra patienter, mellan vårdnivåer och mellan privata och offentliga vårdgivare – hur gör vi det? \n",
  "id": "48955"
}