{
  "title": "Kan digitaliseringen driva fram fler bostäder snabbare?",
  "arranger": "Riksbyggen",
  "times": [
    {
      "start": "2017-07-05T10:00:00.000Z",
      "end": "2017-07-05T10:45:00.000Z"
    }
  ],
  "type": "Samtal",
  "area": "Byggande",
  "language": "Svenska",
  "location": "Teaterskeppet, fartyg",
  "tags": [
    "Bostadsbyggande",
    "Bostadspolitik",
    "Digitalisering",
    "Kommun",
    "Samhällsbyggande"
  ],
  "description": "Den hastiga samhällsomvandlingen drivs till stor del av digitaliseringen. Utvecklingen av nya stadsdelar och bostadsområden går inte lika snabbt. Hur höjer vi blicken mot framtiden för att digitalisera hela samhällsbyggnadsprocessen? ",
  "id": "49030"
}