{
  "title": "Morgondagens hållbara affärsmodeller och näringslivspolitik",
  "arranger": "Tankesmedjan Global Utmaning",
  "times": [
    {
      "start": "2017-07-03T10:45:00.000Z",
      "end": "2017-07-03T11:30:00.000Z"
    }
  ],
  "type": "Seminarium",
  "area": "Näringsliv",
  "language": "Svenska",
  "location": "Almedalens bed and breakfast, Tage Cervins gata 3B",
  "tags": [
    "Agenda 2030",
    "Globala målen",
    "Hållbar utveckling",
    "Innovation"
  ],
  "description": "Hur kan näringslivsaktörer bidra till att vända risker till möjligheter och genom samarbete leda vägen mot en hållbar utveckling?",
  "extendedDescription": "Agenda 2030 och de globala målen skapar en gemensam referensram för hur regeringar, näringsliv och människor vill att en hållbar utveckling i världen ska gestalta sig. Vi ska samtidigt klara att utrota fattigdomen, öka konkurrenskraften och skapar fler jobb, rädda klimatet, uppnå jämställdhet, samt säkerställa utbildning och hälsa för alla. Det handlar om långsiktighet, investeringar och innovationer. Ingen kan nå målen på egenhand och partnerskap är avgörande för genomförandet – inte minst mellan näringsliv och politik.\n",
  "id": "49125"
}