{
  "title": "Digitalt fokus för effektivare insamling",
  "arranger": "Garbergs",
  "times": [
    {
      "start": "2017-07-04T10:00:00.000Z",
      "end": "2017-07-04T11:00:00.000Z"
    }
  ],
  "type": "Seminarium",
  "area": "Digitalisering",
  "language": "Svenska",
  "location": "S:t Hansgatan 5",
  "tags": [
    "Barn och ungdomar",
    "Cancer",
    "Digitalisering",
    "Kommunikation",
    "Välgörenhet"
  ],
  "description": "Hur kan digital analys och syftesdriven kommunikation fördubbla insamlingen? Barncancerfonden inledde 2013 ett brett strategi- och kunskapsarbete med effektanalyser och kartläggning av marknaden. Syftet var att förstå vilka marknadsinsatser som är effektiva.",
  "extendedDescription": "Nya grepp och insikter gjorde att man nådde målet, en fördubbling av insamlade medel, under 2016. Linus delar med sig av case och konkreta exempel på hur Barncancerfonden kraftsamlat kring digitalisering för ökad effekt i sitt kommunikations- och varumärkesarbete.\nLinus Almqvist, kommunikationsdirektör på samhällsrådgivaren Ramböll och tidigare chef för kommunikation och privatinsamling på Barncancerfonden berättar om deras arbete.",
  "id": "49127"
}