{
  "title": "Hur ska vi jobba när chefen är en robot?",
  "arranger": "HejDigitalt",
  "times": [
    {
      "start": "2017-07-06T10:00:00.000Z",
      "end": "2017-07-06T13:00:00.000Z"
    }
  ],
  "type": "Workshop",
  "area": "Digitalisering",
  "language": "Svenska",
  "location": "Volters gränd 8",
  "tags": [
    "Digital transformation",
    "Innovation",
    "Ledarskap",
    "Robot",
    "Robotisering"
  ],
  "description": "Snart kan nära hälften av alla jobb tas över av robotar; i vården, skolan och på kontoret. De tar inte bara över enkla arbetsuppgifter utan blir allt bättre på mellanmänskliga relationer och kan på sikt bli din nya chef. Hur påverkas ledarskap, kommunikation och samarbete av våra digitala kollegor?",
  "extendedDescription": "Finns det områden där det är bättre att ha en robot som chef? Kan smart robotisering bidra till att medarbetare, kunder och användare, oavsett funktionsvariation, bättre inkluderas i samarbete, möten och kommunikation? Hur kan någon med kognitiv funktionsvariation få bättre stöd av en robot-chef?\n\nEn workshop som hjälper oss att identifiera de viktiga sociala och moraliska konsekvenserna av att utnyttja robotar i många delar av samhälle och arbetsliv, inte bara som assistenter utan som chefer och coacher. Workshopen ska resultera i en \"Handbok för robotchefer\".",
  "id": "49281"
}