{
  "title": "Hur utvecklar vi samhället genom innovation?",
  "arranger": "Nationella innovationsrådet",
  "times": [
    {
      "start": "2017-07-03T07:00:00.000Z",
      "end": "2017-07-03T14:00:00.000Z"
    },
    {
      "start": "2017-07-04T07:00:00.000Z",
      "end": "2017-07-04T14:00:00.000Z"
    },
    {
      "start": "2017-07-05T07:00:00.000Z",
      "end": "2017-07-05T14:00:00.000Z"
    },
    {
      "start": "2017-07-06T07:00:00.000Z",
      "end": "2017-07-06T14:00:00.000Z"
    }
  ],
  "type": "Mötes- och debattplats",
  "area": "Näringsliv",
  "language": "Svenska",
  "location": "Hamnplan, H214",
  "tags": [
    "Framtid",
    "Innovation",
    "Samhällsutveckling",
    "Samverkan",
    "Styrning"
  ],
  "description": "Innovationsrådet är en del av regeringens arbete för att stärka Sveriges konkurrenskraft. Hur kan offentlig sektor, näringsliv och akademi främja innovation och gemensamt lösa samhällets utmaningar? Kom och diskutera med oss i tältet, kl 15.00 varje dag bjuder vi även på  intressanta gäster. ",
  "id": "49319"
}