{
  "title": "Digitalt kaos – paradigmskifte i den svenska nyhetsfabriken",
  "arranger": "Kantar Sifo",
  "times": [
    {
      "start": "2017-07-05T10:00:00.000Z",
      "end": "2017-07-05T10:45:00.000Z"
    }
  ],
  "type": "Seminarium",
  "area": "Digitalisering",
  "language": "Svenska",
  "location": "Hamnplan, H201",
  "tags": [
    "Digital transformation",
    "Digitalisering",
    "Kommunikation",
    "Media",
    "Sociala medier"
  ],
  "description": "Svenska konsumenters medievanor förändras snabbt. Detta innebär att spelreglerna för nyheter, kommunikation och information förändrats i grunden. Vi ser betydande skillnader i olika generationer vad det gäller mediekonsumtion. ",
  "extendedDescription": "Detta innebär konkreta affärsmodellsproblem för den svenska medieindustrin vilket i sin tur i förlängningen innebär ett möjligt demokratiproblem där nyheter ekar tyst för de rerdan invigda i slutna ekokammare där endast ens egna åsikter reflekteras..",
  "id": "49430"
}