{
  "title": "Hur ser e-sportare på företagande och politiska sympatier?",
  "arranger": "Goodgame",
  "times": [
    {
      "start": "2017-07-03T10:15:00.000Z",
      "end": "2017-07-03T11:30:00.000Z"
    }
  ],
  "type": "Seminarium",
  "area": "Demokrati",
  "language": "Svenska",
  "location": "Uppsala universitet, Campus Gotland, Cramérgatan 3",
  "tags": [
    "E-handel",
    "Entreprenörskap",
    "Företagande",
    "Nyföretagande",
    "Politiskt engagemang"
  ],
  "description": "Under arbetet med en jämställd e-sportsarena har frågor uppstått kring denna relativt nya grupp i samhället. Hur kan vi förstå dem, är de en homogen grupp och vilka åsikter delar de i olika frågor?  Vi presenterar två nya undersökningar om företagande och olika sympatier bland e-sportare.",
  "id": "49493"
}