{
  "title": "Hur skapar vi en jämställd e-sportsarena?",
  "arranger": "Goodgame",
  "times": [
    {
      "start": "2017-07-03T09:15:00.000Z",
      "end": "2017-07-03T10:30:00.000Z"
    }
  ],
  "type": "Seminarium",
  "area": "Jämställdhet",
  "language": "Svenska",
  "location": "Uppsala universitet, Campus Gotland, Cramérgatan 3",
  "tags": [
    "E-sport",
    "Gaming",
    "Hat",
    "Jämställdhet",
    "Kompetens"
  ],
  "description": "Goodgame presenterar rapporten ”Att skapa en jämställd E-sportsarena” Här behandlas manliga spelares attityder mot kvinnor inom spelvärlden. Fokus läggs på de trakasserier som kvinnliga spelare möts av. Vi lägger också fram en åtgärdsplan på hur vi tror att man kan bemöta problematiken.\n\n",
  "extendedDescription": "Goodgame lägger fram en åtgärdsplan from bl a innehåller en idé om att skapa ett slags ARN för trakasserier och hot där ett gemensamt branschorgan kan arbeta effektivt.\nMan vill också satsa på fler bra arenor för unga som ex Minecraft.\n\nFair Game är ett jämställdhetssamarbete mellan ABF, SESF, NärCon, Goodgame och Unga Örnar.\n",
  "id": "49492"
}