{
  "title": "Den internationella humanitära rätten viktigare än någonsin",
  "arranger": "Svenska Röda Korset",
  "times": [
    {
      "start": "2017-07-05T08:30:00.000Z",
      "end": "2017-07-05T09:15:00.000Z"
    }
  ],
  "type": "Samtal",
  "area": "Säkerhet/försvar",
  "language": "Svenska",
  "location": "Södertorg 17",
  "tags": [
    "Försvar",
    "Humanitära kriser",
    "Internationella relationer",
    "Konflikt",
    "Säkerhetspolitik"
  ],
  "description": "Vi står inför en återuppbyggnad av totalförsvaret, och det innebär att kunskapen om den humanitära rätten behöver öka. Med en helt ny skrift vill Totalförsvarets folkrättsråd bidra till detta och vi samtalar om den humanitära rättens betydelse och hur den regleras internationellt och i Sverige.  ",
  "extendedDescription": "Sedan 150 år finns det internationella regler – den humanitära rätten – som syftar till att humanisera konflikter genom att begränsa det lidande som väpnade konflikter orsakar för såväl civila som stridande. Nu står vi inför en återuppbyggnad av totalförsvaret, vilket innebär att utbildningen och kunskapen i den humanitära rätten behöver öka. \nMed en helt ny skrift vill Totalförsvarets folkrättsråd sprida relevant grundläggande kunskap om den humanitära rätten och samtidigt öka förståelsen för dess viktiga roll för att skydda människors liv och värdighet i väpnade konflikter. Vi samtalar om den humanitära rättens betydelse och hur den regleras internationellt och i Sverige.  \n",
  "id": "49535"
}